{"items":{"serializeList":[{"name":"hay","nr":19412.0},{"name":"wood","nr":61750.0},{"name":"carrot","nr":3794.0},{"name":"pumpkin","nr":13983.0},{"name":"weird_substance","nr":35926.0},{"name":"water","nr":61991.0},{"name":"fertilizer","nr":12693.0}]},"dockedFiles":[],"minimizedFiles":[],"openFilePositions":[{"key":"entity_item_log","value":{"x":-704.9310302734375,"y":860.9805908203125}},{"key":"main","value":{"x":-1593.56640625,"y":729.488525390625}},{"key":"functions","value":{"x":-704.0281982421875,"y":1503.16064453125}},{"key":"docs0","value":{"x":-2283.904296875,"y":1495.75390625}},{"key":"hay","value":{"x":-3134.067138671875,"y":729.2828369140625}},{"key":"wood","value":{"x":-3143.29248046875,"y":350.8497314453125}}],"openFileScrollPositions":[{"key":"entity_item_log","value":-0.0008544921875},{"key":"main","value":-0.000732421875},{"key":"functions","value":149.16009521484376},{"key":"hay","value":0.000823974609375},{"key":"wood","value":-0.0008544921875}],"openFileSizes":[{"key":"entity_item_log","value":{"x":0.0,"y":863.9818115234375}},{"key":"main","value":{"x":0.0,"y":0.0}},{"key":"functions","value":{"x":0.0,"y":0.0}},{"key":"docs0","value":{"x":1561.7598876953125,"y":700.0}},{"key":"hay","value":{"x":0.0,"y":0.0}},{"key":"wood","value":{"x":0.0,"y":0.0}}],"openDocPages":[{"key":"docs0","value":"docs/output.md"}],"unlocks":["grass_5","soil","harvest","pass","do_a_flip","pet_the_piggy","grassland","hay","straw_hat","traffic_cone","while","true","false","break","continue","loops","can_harvest","if","else","elif","speed_5","expand_6","move","north","south","east","west","for","range","get_world_size","change_hat","gray_hat","purple_hat","green_hat","brown_hat","hats","wood","bush","entities","clear","plant","and","or","not","operators","get_entity_type","get_ground_type","grounds","get_pos_x","get_pos_y","none","num_items","items","num_unlocked","senses","print","quick_print","unlocks","str","debug","wizard_hat","carrots_5","carrot","till","can_trade","trade","carrot_seed","trees_5","tree","tree_hat","variables","functions","def","return","global","watering_5","water","use_item","get_water","pumpkin","pumpkin_seed","dead_pumpkin","pumpkins_3","carrot_hat","fertilizer_3","weird_substance","from","import","append","remove","pop","insert","len","list","lists","sunflower_seed","sunflower","power","get_active_power","measure","sunflowers","pumpkin_hat","dicts","sets","add","dict","set","dictionaries","get_cost","costs","unlock","auto_unlock","hedge","treasure","gold","can_move","mazes","get_companion","polyculture","min","max","abs","random","utilities","get_time","get_tick_count","timing","swap","cactus_seed","cactus"],"version":3}